envoxy/__init__.py
envoxy/asserts.py
envoxy/constants.py
envoxy/decorators.py
envoxy/exceptions.py
envoxy/auth/__init__.py
envoxy/auth/backends.py
envoxy/cache/__init__.py
envoxy/cache/redis.py
envoxy/celery/__init__.py
envoxy/celery/client.py
envoxy/couchdb/__init__.py
envoxy/couchdb/client.py
envoxy/db/__init__.py
envoxy/db/dispatcher.py
envoxy/db/exceptions.py
envoxy/db/helpers.py
envoxy/db/orm/__init__.py
envoxy/db/orm/base.py
envoxy/db/orm/constants.py
envoxy/db/orm/helpers.py
envoxy/db/orm/listeners.py
envoxy/db/orm/meta.py
envoxy/db/orm/mixin.py
envoxy/db/orm/schema.py
envoxy/db/orm/session.py
envoxy/db/orm/sqltypes.py
envoxy/db/orm/tests/test_naming_and_listeners.py
envoxy/http/__init__.py
envoxy/http/dispatcher.py
envoxy/mqtt/__init__.py
envoxy/mqtt/dispatcher.py
envoxy/postgresql/__init__.py
envoxy/postgresql/client.py
envoxy/postgresql/sqlalchemy/__init__.py
envoxy/postgresql/sqlalchemy/session.py
envoxy/redis/__init__.py
envoxy/redis/client.py
envoxy/tests/__init__.py
envoxy/tests/fixtures.py
envoxy/tests/test_asserts.py
envoxy/tests/test_concurrency_pool.py
envoxy/tests/test_envoxy_mixin.py
envoxy/tests/test_postgresql_client.py
envoxy/tests/test_validate_models.py
envoxy/tools/__init__.py
envoxy/tools/check_migrations.py
envoxy/tools/validate_models.py
envoxy/tools/alembic/README.md
envoxy/tools/alembic/__init__.py
envoxy/tools/alembic/alembic.ini
envoxy/tools/alembic/cli.py
envoxy/tools/alembic/alembic/__init__.py
envoxy/tools/alembic/alembic/alembic.py
envoxy/tools/alembic/alembic/env.py
envoxy/tools/alembic/alembic/script.py.mako
envoxy/utils/__init__.py
envoxy/utils/cache.py
envoxy/utils/config.py
envoxy/utils/datetime.py
envoxy/utils/encoders.py
envoxy/utils/handlers.py
envoxy/utils/logs.py
envoxy/utils/profiling.py
envoxy/utils/singleton.py
envoxy/utils/throttle.py
envoxy/utils/watchdog.py
envoxy/views/__init__.py
envoxy/views/containers.py
envoxy/views/views.py
envoxy/zeromq/__init__.py
envoxy/zeromq/dispatcher.py
envoxy-0.6.21.dist-info/METADATA
envoxy-0.6.21.dist-info/WHEEL
envoxy-0.6.21.dist-info/entry_points.txt
envoxy-0.6.21.dist-info/top_level.txt
envoxy-0.6.21.dist-info/RECORD
