Metadata-Version: 2.4
Name: envoxy
Version: 0.6.21
Summary: Envoxy Platform Framework
Home-page: https://github.com/habitio/envoxy
Author: Matheus (vorjdux) Santos
Author-email: "Matheus (vorjdux) Santos" <vorj.dux@gmail.com>, Laoska Guadamuz <laoska@benyasca.com>
Project-URL: Homepage, https://github.com/habitio/envoxy
Classifier: License :: OSI Approved :: MIT License
Classifier: Programming Language :: Python :: 3
Classifier: Programming Language :: Python :: 3.12
Classifier: Development Status :: 4 - Beta
Requires-Python: >=3.12
Requires-Dist: cachetools==6.2.1
Requires-Dist: Flask==3.1.2
Requires-Dist: paho-mqtt==2.1.0
Requires-Dist: pika==1.3.2
Requires-Dist: pyzmq==27.1.0
Requires-Dist: requests==2.32.5
Requires-Dist: sdnotify==0.3.2
Requires-Dist: pymongo==4.15.3
Requires-Dist: uPnPClient==1.0.3
Requires-Dist: pylint==4.0.2
Requires-Dist: cffi>=2.0.0
Requires-Dist: psycopg2==2.9.11
Requires-Dist: SQLAlchemy==2.0.44
Requires-Dist: redis==6.4.0
Requires-Dist: flask_cors==6.0.1
Requires-Dist: isort==7.0.0
Requires-Dist: orjson==3.11.3
Requires-Dist: celery==5.5.3
Requires-Dist: amqp==5.3.1
Requires-Dist: celerybeat-mongo==0.2.0
Requires-Dist: inflect==7.5.0
Requires-Dist: alembic==1.17.0
Provides-Extra: dev
Requires-Dist: zipp==3.23.0; extra == "dev"
Requires-Dist: pytest==8.4.2; extra == "dev"
Requires-Dist: twine==6.2.0; extra == "dev"
Requires-Dist: urllib3==2.5.0; extra == "dev"
Requires-Dist: alembic==1.17.0; extra == "dev"
Requires-Dist: pytest-cov==7.0.0; extra == "dev"
Requires-Dist: pytest-asyncio==0.24.0; extra == "dev"
Requires-Dist: pytest-mock==3.14.0; extra == "dev"
Requires-Dist: pytest-xdist==3.8.0; extra == "dev"
Requires-Dist: coverage[toml]>=7.6.0; extra == "dev"
Requires-Dist: pre-commit>=4.0.0; extra == "dev"
Requires-Dist: ruff>=0.7.0; extra == "dev"
Requires-Dist: mypy>=1.14.0; extra == "dev"
Requires-Dist: bandit[toml]>=1.8.0; extra == "dev"
Requires-Dist: safety>=3.2.0; extra == "dev"
Requires-Dist: pip-audit>=2.7.0; extra == "dev"
Provides-Extra: test
Requires-Dist: pytest==8.4.2; extra == "test"
Requires-Dist: pytest-cov==7.0.0; extra == "test"
Requires-Dist: pytest-asyncio==0.24.0; extra == "test"
Requires-Dist: pytest-mock==3.14.0; extra == "test"
Requires-Dist: pytest-xdist==3.8.0; extra == "test"
Requires-Dist: coverage[toml]>=7.6.0; extra == "test"
Provides-Extra: journald
Requires-Dist: cysystemd>=2.0.1; extra == "journald"
Dynamic: author
Dynamic: home-page
Dynamic: requires-python
